pyopentdb/__init__.py
pyopentdb/api/OpenTDBClient.py
pyopentdb/api/__init__.py
pyopentdb/enum/Category.py
pyopentdb/enum/Difficulty.py
pyopentdb/enum/QuestionType.py
pyopentdb/enum/ResponseCode.py
pyopentdb/enum/__init__.py
pyopentdb/exc/APIError.py
pyopentdb/exc/QuestionError.py
pyopentdb/exc/__init__.py
pyopentdb/model/Question.py
pyopentdb/model/QuestionResponse.py
pyopentdb/model/QuestionResult.py
pyopentdb/model/QuestionSet.py
pyopentdb/model/__init__.py
pyopentdb/scripts/__init__.py
pyopentdb/scripts/get_categories.py
pyopentdb-0.0.4.dist-info/LICENSE
pyopentdb-0.0.4.dist-info/METADATA
pyopentdb-0.0.4.dist-info/WHEEL
pyopentdb-0.0.4.dist-info/top_level.txt
pyopentdb-0.0.4.dist-info/RECORD
