Metadata-Version: 2.1
Name: pyopentdb
Version: 0.0.4
Summary: Python interface for the Open Trivia DB
Home-page: https://github.com/amickael/pyopentdb
Author: Andrew Mickael
Author-email: andrew.mickael@gmail.com
License: MIT
Platform: NT
Platform: POSIX
Classifier: Programming Language :: Python :: 3
Classifier: License :: OSI Approved :: MIT License
Classifier: Operating System :: MacOS :: MacOS X
Classifier: Operating System :: POSIX
Classifier: Operating System :: Microsoft :: Windows
Requires-Python: >=3.6
Requires-Dist: requests
